mindspawner/__init__.py
mindspawner/mindspawner.py
mindspawner-0.2.4.dist-info/METADATA
mindspawner-0.2.4.dist-info/WHEEL
mindspawner-0.2.4.dist-info/top_level.txt
mindspawner-0.2.4.dist-info/RECORD
