Metadata-Version: 2.1
Name: mindspawner
Version: 0.2.4
Summary: A Python library to interact with the MindSpawner agent server
Home-page: https://github.com/professorASU/mindspawner-python
Author: Tomoyoshi Yamamoto
Author-email: karolus@sfc.wide.ad.jp
Classifier: Programming Language :: Python :: 3
Classifier: License :: OSI Approved :: MIT License
Classifier: Operating System :: OS Independent
Requires-Python: >=3.6
Requires-Dist: python-socketio
Requires-Dist: numpy
